{"cameraMode":{"drawMode":0,"name":"Shaded","section":"Shading Mode"},"sceneLighting":false,"audioPlay":false,"sceneViewState":{"m_AlwaysRefresh":false,"showFog":true,"showSkybox":false,"showFlares":true,"showImageEffects":true,"showParticleSystems":true,"showVisualEffectGraphs":true,"m_FxEnabled":true},"in2DMode":false,"pivot":{"x":614.0,"y":247.49998474121095,"z":0.0},"rotation":{"x":0.022792935371398927,"y":0.03353635221719742,"z":-0.0007858414901420474,"w":0.9991896748542786},"size":662.0062255859375,"orthographic":false}